ViewNudger/__init__.py
ViewNudger/api.py
ViewNudger/logger.py
ViewNudger/ui/__init__.py
ViewNudger/ui/style.css
ViewNudger/ui/ui.py
ViewNudger/ui/utils.py
ViewNudger/ui/widgets.py
ViewNudger/ui/icons/nudgeDownLeft_hover.png
ViewNudger/ui/icons/nudgeDownLeft_normal.png
ViewNudger/ui/icons/nudgeDownRight_hover.png
ViewNudger/ui/icons/nudgeDownRight_normal.png
ViewNudger/ui/icons/nudgeDown_hover.png
ViewNudger/ui/icons/nudgeDown_normal.png
ViewNudger/ui/icons/nudgeLeft_hover.png
ViewNudger/ui/icons/nudgeLeft_normal.png
ViewNudger/ui/icons/nudgeRight_hover.png
ViewNudger/ui/icons/nudgeRight_normal.png
ViewNudger/ui/icons/nudgeUpLeft_hover.png
ViewNudger/ui/icons/nudgeUpLeft_normal.png
ViewNudger/ui/icons/nudgeUpRight_hover.png
ViewNudger/ui/icons/nudgeUpRight_normal.png
ViewNudger/ui/icons/nudgeUp_hover.png
ViewNudger/ui/icons/nudgeUp_normal.png
ViewNudger-0.1.12.dist-info/DESCRIPTION.rst
ViewNudger-0.1.12.dist-info/METADATA
ViewNudger-0.1.12.dist-info/RECORD
ViewNudger-0.1.12.dist-info/WHEEL
ViewNudger-0.1.12.dist-info/metadata.json
ViewNudger-0.1.12.dist-info/top_level.txt
