Metadata-Version: 2.0
Name: ViewNudger
Version: 0.1.12
Summary: A Maya Camera or Object pixel nudger.
Home-page: https://github.com/chrisdevito/ViewNudger
Author: Christopher DeVito
Author-email: chrisdevito@chribis.com
License: MIT
Platform: UNKNOWN
Classifier: Development Status :: 3 - Alpha
Classifier: Intended Audience :: Developers
Classifier: License :: OSI Approved :: MIT License
Classifier: Natural Language :: English
Classifier: Operating System :: OS Independent
Classifier: Programming Language :: Python
Classifier: Programming Language :: Python :: 2
